{
    "display": {
      "icon": {
        "id": "minecraft:clock"
      },
      "title": "Down Memory Lane",
      "description": "Revisit 8 Years of Existence History on The Terraces",
      "show_toast": true,
      "announce_to_chat": true,
      "hidden": false
    },
    "parent": "existence_smp:locations/high_tide",
    "criteria": {
      "requirement": {
        "trigger": "minecraft:location",
        "conditions": {
          "player": [
            {
              "condition": "minecraft:entity_properties",
              "entity": "this",
              "predicate": {
                "location": {
                  "position": {
                    "x": {
                      "min": -230,
                      "max": -175
                    },
                    "y": {
                      "min": 72,
                      "max": 105
                    },
                    "z": {
                      "min": -230,
                      "max": -155
                    }
                  },
                  "dimension": "minecraft:overworld"
                }
              }
            }
          ]
        }
      }
    }
  }
  